federatedidentity/__init__.py
federatedidentity/_oidc.py
federatedidentity/_verify.py
federatedidentity/exceptions.py
federatedidentity/transport/__init__.py
federatedidentity/transport/requests.py
federatedidentity/verifiers.py
verify_oidc_identity-0.4.38.dist-info/METADATA
verify_oidc_identity-0.4.38.dist-info/WHEEL
verify_oidc_identity-0.4.38.dist-info/licenses/LICENSE.txt
verify_oidc_identity-0.4.38.dist-info/RECORD
