Metadata-Version: 2.4
Name: verify-oidc-identity
Version: 0.4.38
Summary: Verify OIDC JWT identity tokens using OIDC discovery
License: MIT
License-File: LICENSE.txt
Author: Rich Wareham
Author-email: rich.verify-oidc-identity@richwareham.com
Requires-Python: >=3.10,<4.0
Classifier: License :: OSI Approved :: MIT License
Classifier: Programming Language :: Python :: 3
Classifier: Programming Language :: Python :: 3.10
Classifier: Programming Language :: Python :: 3.11
Classifier: Programming Language :: Python :: 3.12
Classifier: Programming Language :: Python :: 3.13
Classifier: Programming Language :: Python :: 3.14
Requires-Dist: jwcrypto (>=1.5.6,<2.0.0)
Requires-Dist: validators (>=0.35.0,<0.36.0)
Project-URL: Changelog, https://github.com/rjw57/verify-oidc-identity/blob/main/CHANGELOG.md
Project-URL: Documentation, https://rjw57.github.io/verify-oidc-identity
Project-URL: Homepage, https://github.com/rjw57/verify-oidc-identity
Project-URL: Issues, https://github.com/rjw57/verify-oidc-identity/issues
Project-URL: Repository, https://github.com/rjw57/verify-oidc-identity.git
